SingleEndpointGateway/__init__.py
SingleEndpointGateway/server.py
singleendpointgateway-0.0.2.dist-info/LICENSE
singleendpointgateway-0.0.2.dist-info/METADATA
singleendpointgateway-0.0.2.dist-info/WHEEL
singleendpointgateway-0.0.2.dist-info/RECORD
