Metadata-Version: 2.1
Name: SingleEndpointGateway
Version: 0.0.2
Summary: A simple single‑endpoint FastAPI gateway with caching
Home-page: https://github.com/dsharathrao/SingleEndpointGateway
License: MIT
Author: Sharath Kumar
Author-email: dsharathrao@gmail.com
Requires-Python: >=3.8
Classifier: Development Status :: 3 - Alpha
Classifier: Environment :: Console
Classifier: Intended Audience :: Developers
Classifier: License :: OSI Approved :: MIT License
Classifier: Operating System :: MacOS
Classifier: Operating System :: Microsoft :: Windows
Classifier: Operating System :: POSIX :: Linux
Classifier: Programming Language :: Python :: 3
Classifier: Programming Language :: Python :: 3.8
Classifier: Programming Language :: Python :: 3.9
Classifier: Programming Language :: Python :: 3.10
Classifier: Programming Language :: Python :: 3.11
Classifier: Programming Language :: Python :: 3.12
Classifier: Programming Language :: Python :: 3.13
Requires-Dist: fastapi (>=0.110,<0.111)
Requires-Dist: httpx (>=0.27,<0.28)
Requires-Dist: pyyaml (>=6.0,<7.0)
Requires-Dist: uvicorn[standard] (>=0.27,<0.28)
Project-URL: Bug Tracker, https://github.com/dsharathrao/SingleEndpointGateway/issues
Project-URL: Repository, https://github.com/dsharathrao/SingleEndpointGateway
